dev5334_package_test/__init__.py
dev5334_package_test/myfunction_version.py
dev5334_package_test-0.1.2.dist-info/METADATA
dev5334_package_test-0.1.2.dist-info/WHEEL
dev5334_package_test-0.1.2.dist-info/top_level.txt
dev5334_package_test-0.1.2.dist-info/RECORD
